{"data":{"author_id":"911518995735396352","created_at":"2023-05-22T13:53:54.000Z","edit_history_tweet_ids":["1660645162370887681"],"id":"1660645162370887681","public_metrics":{"retweet_count":0,"reply_count":1,"like_count":2,"quote_count":0,"impression_count":0},"text":"Dogepound https://t.co/WvWC5AOJrV"},"includes":{"users":[{"id":"911518995735396352","name":"thepinkmon","profile_image_url":"https://pbs.twimg.com/profile_images/1656339292027748359/MCdPD5t5_normal.jpg","username":"dalankopeh"}]},"matching_rules":[{"id":"1660644952106233877","tag":""},{"id":"1660644952106233874","tag":""},{"id":"1660644952106233875","tag":""}],"media_url":"https://pbs.twimg.com/media/FwvL97dX0AQOJvw.png"}